MANIFEST.in
README.md
setup.py
django_moneta.egg-info/PKG-INFO
django_moneta.egg-info/SOURCES.txt
django_moneta.egg-info/dependency_links.txt
django_moneta.egg-info/requires.txt
django_moneta.egg-info/top_level.txt
moneta/__init__.py
moneta/models.py
moneta/signals.py
moneta/transport.py