Metadata-Version: 1.1
Name: django-moneta
Version: 0.1
Summary: Django app for Moneta eTerminal API.
Home-page: https://github.com/visionect/django-moneta
Author: Visionect d.o.o., Matevz Mihalic
Author-email: matevz.mihalic@visionect.si
License: MIT
Keywords: moneta django api eterminal
Platform: UNKNOWN
Classifier: Development Status :: 4 - Beta
Classifier: Environment :: Web Environment
Classifier: Intended Audience :: Developers
Classifier: License :: OSI Approved :: MIT License
Classifier: Operating System :: OS Independent
Classifier: Programming Language :: Python
Classifier: Framework :: Django
